<?xml version="1.0" encoding="utf-8"?>
<Dependencies>
  <Source Uri="https://github.com/maestro-auth-test/dotnet" Mapping="templating" Sha="15802c5dfa893b68812be272d93e7feecee2c87c" BarId="79" />
  <ProductDependencies>
    <!-- Intermediate is necessary for source build. -->
    <Dependency Name="Microsoft.SourceBuild.Intermediate.source-build-externals" Version="10.0.621401">
      <Uri>https://github.com/dotnet/source-build-externals</Uri>
      <Sha>d64d8da45618323a39fb77860d1140bdbcd506ad</Sha>
      <SourceBuild RepoName="source-build-externals" ManagedOnly="true" />
    </Dependency>
    <!-- Intermediate is necessary for source build. -->
    <Dependency Name="Microsoft.SourceBuild.Intermediate.source-build-reference-packages" Version="10.0.621401">
      <Uri>https://github.com/dotnet/source-build-reference-packages</Uri>
      <Sha>0fb2d0d836dffe32b32e362e86f0dccd6f40bee8</Sha>
      <SourceBuild RepoName="source-build-reference-packages" ManagedOnly="true" />
    </Dependency>
    <Dependency Name="System.CommandLine" Version="2.0.0-beta4.25215.102">
      <Uri>https://github.com/maestro-auth-test/dotnet</Uri>
      <Sha>15802c5dfa893b68812be272d93e7feecee2c87c</Sha>
    </Dependency>
  </ProductDependencies>
  <ToolsetDependencies>
    <Dependency Name="Microsoft.DotNet.Arcade.Sdk" Version="10.0.0-beta.25215.102">
      <Uri>https://github.com/maestro-auth-test/dotnet</Uri>
      <Sha>15802c5dfa893b68812be272d93e7feecee2c87c</Sha>
    </Dependency>
    <!-- Intermediate is necessary for source build. -->
    <Dependency Name="Microsoft.SourceBuild.Intermediate.arcade" Version="10.0.0-beta.25214.8">
      <Uri>https://github.com/dotnet/arcade</Uri>
      <Sha>5af24911dd2de348e66143167d66d05eb55a9db6</Sha>
      <SourceBuild RepoName="arcade" ManagedOnly="true" />
    </Dependency>
    <!-- Dependencies required for source build. We'll still update manually -->
    <Dependency Name="System.Formats.Asn1" Version="10.0.0-preview.4.25215.102">
      <Uri>https://github.com/maestro-auth-test/dotnet</Uri>
      <Sha>15802c5dfa893b68812be272d93e7feecee2c87c</Sha>
    </Dependency>
    <Dependency Name="Microsoft.Extensions.Logging" Version="10.0.0-preview.4.25215.102">
      <Uri>https://github.com/maestro-auth-test/dotnet</Uri>
      <Sha>15802c5dfa893b68812be272d93e7feecee2c87c</Sha>
    </Dependency>
    <Dependency Name="Microsoft.Extensions.Logging.Abstractions" Version="10.0.0-preview.4.25215.102">
      <Uri>https://github.com/maestro-auth-test/dotnet</Uri>
      <Sha>15802c5dfa893b68812be272d93e7feecee2c87c</Sha>
    </Dependency>
    <Dependency Name="Microsoft.Extensions.Logging.Console" Version="10.0.0-preview.4.25215.102">
      <Uri>https://github.com/maestro-auth-test/dotnet</Uri>
      <Sha>15802c5dfa893b68812be272d93e7feecee2c87c</Sha>
    </Dependency>
    <Dependency Name="Microsoft.Extensions.DependencyInjection.Abstractions" Version="10.0.0-preview.4.25215.102">
      <Uri>https://github.com/maestro-auth-test/dotnet</Uri>
      <Sha>15802c5dfa893b68812be272d93e7feecee2c87c</Sha>
    </Dependency>
    <Dependency Name="Microsoft.Bcl.AsyncInterfaces" Version="10.0.0-preview.4.25215.102">
      <Uri>https://github.com/maestro-auth-test/dotnet</Uri>
      <Sha>15802c5dfa893b68812be272d93e7feecee2c87c</Sha>
    </Dependency>
    <Dependency Name="System.Diagnostics.DiagnosticSource" Version="10.0.0-preview.4.25215.102">
      <Uri>https://github.com/maestro-auth-test/dotnet</Uri>
      <Sha>15802c5dfa893b68812be272d93e7feecee2c87c</Sha>
    </Dependency>
    <Dependency Name="System.Text.Json" Version="10.0.0-preview.4.25215.102">
      <Uri>https://github.com/maestro-auth-test/dotnet</Uri>
      <Sha>15802c5dfa893b68812be272d93e7feecee2c87c</Sha>
    </Dependency>
    <Dependency Name="System.IO.Pipelines" Version="10.0.0-preview.4.25215.102">
      <Uri>https://github.com/maestro-auth-test/dotnet</Uri>
      <Sha>15802c5dfa893b68812be272d93e7feecee2c87c</Sha>
    </Dependency>
    <Dependency Name="System.Text.Encodings.Web" Version="10.0.0-preview.4.25215.102">
      <Uri>https://github.com/maestro-auth-test/dotnet</Uri>
      <Sha>15802c5dfa893b68812be272d93e7feecee2c87c</Sha>
    </Dependency>
  </ToolsetDependencies>
</Dependencies>
